ovos_face_embeddings/__init__.py
ovos_face_embeddings/version.py
ovos_face_embeddings_plugin-0.0.0a2.dist-info/METADATA
ovos_face_embeddings_plugin-0.0.0a2.dist-info/WHEEL
ovos_face_embeddings_plugin-0.0.0a2.dist-info/entry_points.txt
ovos_face_embeddings_plugin-0.0.0a2.dist-info/top_level.txt
ovos_face_embeddings_plugin-0.0.0a2.dist-info/zip-safe
ovos_face_embeddings_plugin-0.0.0a2.dist-info/RECORD
