Metadata-Version: 2.1
Name: ovos-face-embeddings-plugin
Version: 0.0.0a2
Summary: A face recognition plugin for OVOS
Home-page: https://github.com/TigreGotico/ovos-face-embeddings-plugin
Author: jarbasai
Author-email: jarbasai@mailfence.com
License: MIT
Keywords: OVOS openvoiceos plugin face recognition
Platform: UNKNOWN
Requires-Dist: ovos-plugin-manager
Requires-Dist: numpy
Requires-Dist: face-recognition
Requires-Dist: ovos-chromadb-embeddings-plugin
